README.md
setup.py
linkedin_auto_unfollow_company/__init__.py
linkedin_auto_unfollow_company.egg-info/PKG-INFO
linkedin_auto_unfollow_company.egg-info/SOURCES.txt
linkedin_auto_unfollow_company.egg-info/dependency_links.txt
linkedin_auto_unfollow_company.egg-info/requires.txt
linkedin_auto_unfollow_company.egg-info/top_level.txt