Metadata-Version: 2.1
Name: linkedin-auto-unfollow-company
Version: 1.0.0
Summary: A python library to unfollow company on linkedin automatically.
Home-page: https://linkedin-api.datakund.com/en/latest/
Author: DataKund
Author-email: datakund@gmail.com
License: Apache License 2.0
Keywords: linkedin python bot_studio automation unfollow company login
Platform: UNKNOWN
